radssh/__init__.py
radssh/__main__.py
radssh/authmgr.py
radssh/config.py
radssh/console.py
radssh/dispatcher.py
radssh/hostkey.py
radssh/keepalive.py
radssh/known_hosts.py
radssh/pkcs.py
radssh/shell.py
radssh/ssh.py
radssh/star_commands.py
radssh/streambuffer.py
radssh/plugins/__init__.py
radssh/plugins/__main__.py
radssh/plugins/add_drop.py
radssh/plugins/alias.py
radssh/plugins/auth.py
radssh/plugins/banner.py
radssh/plugins/file_lookup.py
radssh/plugins/formatters.py
radssh/plugins/genders_plugin.py
radssh/plugins/grep.py
radssh/plugins/ip.py
radssh/plugins/jumpbox.py
radssh/plugins/lines.py
radssh/plugins/sftp.py
radssh/plugins/ssh_key.py
radssh/plugins/star_cd.py
radssh/plugins/star_tty.py
radssh/plugins/swedish_chef.py
radssh/plugins/tar.py
radssh/plugins/vcr.py
radssh-1.1.2.dist-info/DESCRIPTION.rst
radssh-1.1.2.dist-info/METADATA
radssh-1.1.2.dist-info/RECORD
radssh-1.1.2.dist-info/WHEEL
radssh-1.1.2.dist-info/metadata.json
radssh-1.1.2.dist-info/top_level.txt
