Metadata-Version: 2.0
Name: radssh
Version: 1.1.2
Summary: RadSSH Module
Home-page: https://github.com/radssh/radssh
Author: Paul Kapp
Author-email: paul.kapp@risk.lexisnexis.com
License: BSD
Keywords: ssh parallel paramiko
Platform: UNKNOWN
Classifier: Development Status :: 5 - Production/Stable
Classifier: Environment :: Console
Classifier: Intended Audience :: System Administrators
Classifier: Intended Audience :: Developers
Classifier: License :: OSI Approved :: BSD License
Classifier: Operating System :: POSIX
Classifier: Operating System :: Microsoft :: Windows
Classifier: Operating System :: MacOS :: MacOS X
Classifier: Programming Language :: Python :: 2
Classifier: Programming Language :: Python :: 2.6
Classifier: Programming Language :: Python :: 2.7
Classifier: Programming Language :: Python :: 3
Classifier: Programming Language :: Python :: 3.3
Classifier: Programming Language :: Python :: 3.4
Classifier: Programming Language :: Python :: 3.5
Classifier: Programming Language :: Python :: 3.6
Classifier: Topic :: System :: Shells
Classifier: Topic :: Utilities
Requires-Dist: paramiko
Requires-Dist: netaddr
